{"type":"FeatureCollection","features":[{"type":"Feature","geometry":{"type":"Point","coordinates":[-64.19504642486574,10.432822509841568]},"properties":{"name":"UDO"}},{"type":"Feature","geometry":{"type":"Point","coordinates":[-64.18529391288759,10.44935621732156]},"properties":{"name":"UNEFA"}},{"type":"Feature","geometry":{"type":"Point","coordinates":[-64.14081215858461,10.438203710881432]},"properties":{"name":"UPTOS"}}]}